boosh/__init__.py
boosh/config.py
boosh/exceptions.py
boosh/ssh.py
boosh/test_config.py
boosh/test_ssh.py
boosh-0.1.0.dev1.dist-info/DESCRIPTION.rst
boosh-0.1.0.dev1.dist-info/entry_points.txt
boosh-0.1.0.dev1.dist-info/METADATA
boosh-0.1.0.dev1.dist-info/metadata.json
boosh-0.1.0.dev1.dist-info/RECORD
boosh-0.1.0.dev1.dist-info/top_level.txt
boosh-0.1.0.dev1.dist-info/WHEEL
