Metadata-Version: 2.0
Name: boosh
Version: 0.1.0.dev1
Summary: SSH to your your private EC2 instances by ID
Home-page: https://github.com/betaworks/boosh
Author: Paul Handly
Author-email: ph@betaworks.com
License: MIT
Keywords: ec2,ssh,shell,aws,bastion,firewall,proxy
Platform: UNKNOWN
Classifier: Development Status :: 4 - Beta
Classifier: Environment :: Console
Classifier: Intended Audience :: Developers
Classifier: Intended Audience :: System Administrators
Classifier: License :: OSI Approved :: MIT License
Classifier: Operating System :: OS Independent
Classifier: Programming Language :: Python :: 2 :: Only
Classifier: Programming Language :: Python :: 2
Classifier: Programming Language :: Python :: 2.7
Classifier: Programming Language :: Python
Classifier: Topic :: Utilities
Requires-Dist: botocore (>=0.94.0)
